[
    {
        "id": "earth",
        "name": "Earth Tower",
        "cost": 10,
        "damage": 5,
        "firing_rate": 1.0,
        "range": 3,
        "color": [101, 67, 33],
        "unlocked": true,
        "description": "A sturdy tower made of rock and soil. Slow but reliable. Good for early waves."
    },
    {
        "id": "fire",
        "name": "Fire Tower",
        "cost": 25,
        "damage": 15,
        "firing_rate": 1.5,
        "range": 4,
        "color": [210, 120, 30],
        "unlocked": true,
        "description": "Burns enemies with intense heat. High damage but costs more to build."
    },
    {
        "id": "water",
        "name": "Water Tower",
        "cost": 20,
        "damage": 10,
        "firing_rate": 2.0,
        "range": 3,
        "color": [50, 100, 220],
        "unlocked": true,
        "description": "Slows enemies with a torrent of water while dealing moderate damage."
    },
    {
        "id": "wind",
        "name": "Wind Tower",
        "cost": 30,
        "damage": 12,
        "firing_rate": 2.5,
        "range": 5,
        "color": [180, 180, 180],
        "unlocked": true,
        "description": "Pushes enemies back with gale-force blasts. Can hit multiple targets."
    },
    {
        "id": "ice",
        "name": "Ice Tower",
        "cost": 35,
        "damage": 8,
        "firing_rate": 0.8,
        "range": 3,
        "color": [160, 220, 255],
        "unlocked": true,
        "description": "Freezes enemies solid. Low damage but hard-freezes targets in place."
    },
    {
        "id": "lava",
        "name": "Lava Tower",
        "cost": 45,
        "damage": 22,
        "firing_rate": 0.6,
        "range": 4,
        "color": [200, 50, 10],
        "unlocked": true,
        "description": "Erupts molten rock at enemies. Devastating damage but very slow to fire."
    },
    {
        "id": "spirit",
        "name": "Spirit Tower",
        "cost": 60,
        "damage": 18,
        "firing_rate": 3.0,
        "range": 6,
        "color": [180, 100, 255],
        "unlocked": true,
        "description": "Channels ethereal energy. Fast fire rate and the longest range of all towers."
    },
    {
        "id": "t8",
        "name": "???",
        "cost": 0,
        "damage": 0,
        "firing_rate": 0,
        "range": 0,
        "color": [100, 100, 100],
        "unlocked": true,
        "description": "Not yet discovered."
    },
    {
        "id": "t9",
        "name": "???",
        "cost": 0,
        "damage": 0,
        "firing_rate": 0,
        "range": 0,
        "color": [100, 100, 100],
        "unlocked": false,
        "description": "Not yet discovered."
    },
    {
        "id": "t10",
        "name": "???",
        "cost": 0,
        "damage": 0,
        "firing_rate": 0,
        "range": 0,
        "color": [100, 100, 100],
        "unlocked": false,
        "description": "Not yet discovered."
    }
]
